skopi/__init__.py
skopi/aggregate.py
skopi/build_autoranging_frames.py
skopi/constants.py
skopi/crosstalk.py
skopi/diffraction.py
skopi/ff_waaskirf_database.py
skopi/particle.py
skopi/particleCollection.py
skopi/particlePlacement.py
skopi/radiationDamage.py
skopi/radiationDamageMPI.py
skopi/saxs.py
skopi/util.py
skopi/visualizer.py
skopi/beam/__init__.py
skopi/beam/base.py
skopi/beam/convert.py
skopi/beam/sase.py
skopi/datasets/__init__.py
skopi/datasets/spidata.py
skopi/detector/__init__.py
skopi/detector/autoranging.py
skopi/detector/base.py
skopi/detector/cspad.py
skopi/detector/epix10k.py
skopi/detector/jungfrau.py
skopi/detector/lcls.py
skopi/detector/plain.py
skopi/detector/pnccd.py
skopi/detector/simple_square.py
skopi/detector/user_defined.py
skopi/experiment/__init__.py
skopi/experiment/base.py
skopi/experiment/fxs.py
skopi/experiment/holo.py
skopi/experiment/spi.py
skopi/geometry/__init__.py
skopi/geometry/convert.py
skopi/geometry/generate.py
skopi/geometry/mapping.py
skopi/geometry/merge.py
skopi/geometry/slice_.py
skopi/gpu/__init__.py
skopi/gpu/diffraction.py
skopi-0.6.0.dist-info/LICENSE.md
skopi-0.6.0.dist-info/METADATA
skopi-0.6.0.dist-info/WHEEL
skopi-0.6.0.dist-info/top_level.txt
skopi-0.6.0.dist-info/RECORD
