Metadata-Version: 2.1
Name: skopi
Version: 0.6.0
Summary: Single particle imaging simulation package
Home-page: https://github.com/chuckie82/skopi.git
Maintainer: Chunhong Yoon
Maintainer-email: yoon82@stanford.edu
License: UNKNOWN
Platform: UNKNOWN
Classifier: Programming Language :: Python :: 3
Classifier: Operating System :: OS Independent
License-File: LICENSE.md
Requires-Dist: numpy
Requires-Dist: numba
Requires-Dist: scipy
Requires-Dist: mpi4py
Requires-Dist: h5py
Requires-Dist: six
Requires-Dist: scikit-learn
Requires-Dist: pytest
Requires-Dist: matplotlib
Requires-Dist: setuptools
Requires-Dist: gdown
